gatorpy/.DS_Store
gatorpy/UNet.py
gatorpy/__init__.py
gatorpy/addPredictions.py
gatorpy/archives/UNet-02032023.py
gatorpy/archives/gator-01272023.py
gatorpy/archives/toolbox-02032023/GPUselect.py
gatorpy/archives/toolbox-02032023/PartitionOfImage.py
gatorpy/archives/toolbox-02032023/PartitionOfImageOM.py
gatorpy/archives/toolbox-02032023/ftools.py
gatorpy/archives/toolbox-02032023/imtools.py
gatorpy/archives/toolbox-02032023/toolbox.py
gatorpy/cloneFolder.py
gatorpy/gator.py
gatorpy/gatorExport.py
gatorpy/gatorObject.py
gatorpy/gatorPhenotype.py
gatorpy/gatorPipeline.py
gatorpy/gatorPredict.py
gatorpy/gatorTrain.py
gatorpy/generateGatorScore.py
gatorpy/generateThumbnails.py
gatorpy/generateTrainTestSplit.py
gatorpy/mergeGatorObject.py
gatorpy/scatterPlot.py
gatorpy/toolbox/GPUselect.py
gatorpy/toolbox/PartitionOfImage.py
gatorpy/toolbox/__init__.py
gatorpy/toolbox/ftools.py
gatorpy/toolbox/imtools.py
gatorpy-0.1.16.dist-info/METADATA
gatorpy-0.1.16.dist-info/WHEEL
gatorpy-0.1.16.dist-info/RECORD
